{
  "aliases": [
    {
      "alias": "96403eda21f1efd4",
      "aliasId": "hz.web.96403eda21f1efd4.alias.1",
      "canonical": "aquarel.nu"
    },
    {
      "alias": "aquarel.nu",
      "aliasId": "hz.web.96403eda21f1efd4.alias.2",
      "canonical": "aquarel.nu"
    },
    {
      "alias": "web 96403eda21f1efd4",
      "aliasId": "hz.web.96403eda21f1efd4.alias.3",
      "canonical": "aquarel.nu"
    }
  ],
  "app": "assistant",
  "confidence": 0.71,
  "docId": "hz.web.96403eda21f1efd4",
  "domain": "web",
  "entities": [
    {
      "entityId": "hz.web.96403eda21f1efd4.entity.1",
      "kind": "document",
      "name": "aquarel.nu",
      "tokens": [
        "aquarel",
        "nu"
      ]
    },
    {
      "entityId": "hz.web.96403eda21f1efd4.entity.2",
      "kind": "heading",
      "name": "aquarel.nu",
      "tokens": [
        "aquarel",
        "nu"
      ]
    },
    {
      "entityId": "hz.web.96403eda21f1efd4.entity.3",
      "kind": "heading",
      "name": "Summary",
      "tokens": [
        "summary"
      ]
    },
    {
      "entityId": "hz.web.96403eda21f1efd4.entity.4",
      "kind": "heading",
      "name": "Keywords",
      "tokens": [
        "keywords"
      ]
    },
    {
      "entityId": "hz.web.96403eda21f1efd4.entity.5",
      "kind": "heading",
      "name": "Excerpt",
      "tokens": [
        "excerpt"
      ]
    }
  ],
  "facts": [
    {
      "charEnd": 60,
      "charStart": 15,
      "factId": "hz.web.96403eda21f1efd4.fact.1",
      "kind": "summary",
      "text": "Source: https://aquarel.nu/assets/css/css.css",
      "tokens": [
        "source",
        "https",
        "aquarel",
        "nu",
        "assets",
        "css",
        "css",
        "css"
      ]
    },
    {
      "charEnd": 351,
      "charStart": 112,
      "factId": "hz.web.96403eda21f1efd4.fact.1",
      "kind": "bullet",
      "text": "/* * ================================ * Copyright (c) by Aelyn <https://aelysia.net> and Cerine <https://caelestis.nu> * * This domain exists in a state of continual development, and its governing codes * are subject to ongoing revision.",
      "tokens": [
        "copyright",
        "aelyn",
        "https",
        "aelysia",
        "net",
        "cerine",
        "https",
        "caelestis",
        "nu",
        "domain",
        "exists",
        "state",
        "continual",
        "development",
        "its",
        "governing",
        "codes",
        "subject",
        "ongoing",
        "revision"
      ]
    },
    {
      "charEnd": 515,
      "charStart": 352,
      "factId": "hz.web.96403eda21f1efd4.fact.2",
      "kind": "bullet",
      "text": "While critical study and analytical engagement * are permitted, any form of reproduction, appropriation, or misattribution of * this work is strictly prohibited.",
      "tokens": [
        "while",
        "critical",
        "study",
        "analytical",
        "engagement",
        "permitted",
        "any",
        "form",
        "reproduction",
        "appropriation",
        "misattribution",
        "work",
        "strictly",
        "prohibited"
      ]
    },
    {
      "charEnd": 4526,
      "charStart": 516,
      "factId": "hz.web.96403eda21f1efd4.fact.3",
      "kind": "bullet",
      "text": "* ================================ */ /* ================================ FONTS ================================ */ @import url('https://fonts.googleapis.com/css2?family=Fira+Sans&display=swap'); /* ================================ GLOBALS ================================ */ div#qTip { background: #fefefe; font: normal 0.8em 'Fira Sans', sans-serif; line-height: 20px; color: #444; display: none; padding: 10px; z-index: 1000; text-shadow: none; text-align: justify; position: absolute; border: 0; border-radius: 5px; max-width: 350px; } .req { color: #ff0000; } .imp { color: #ff0000; font-weight: bold; } .showCredit, .form-check { display: none; } .center { display: flex; justify-content: center; gap: 1px; flex-wrap: wrap; align-items: center; } .stat { width: 100%; text-align: center; } /* ================================ FORMS ================================ */ .select optgroup { font-weight: normal; font-style: normal; } .form { font-size: 1rem; margin: 0 auto; width: 750px; text-align: center; display: flex; flex-wrap: wrap; gap: 20px; justify-content: space-between; } .form-inline { display: flex; flex-direction: column; gap: 0px; box-sizing: border-box; width: 48%; margin-bottom: 10px; margin-top: auto; } .form-inline label, .form-inline div.label { display: block; margin: 0px; } .form-inline input, .form-inline select { width: 100%; padding: 0.8em; margin-top: 5px; margin-bottom: 10px; box-sizing: border-box; font-size: 1rem; } .pw-container { display: flex; gap: 20px; } .pw-group { flex: 1; display: flex; flex-direction: column; } .pw-group label { margin-bottom: 5px; } .pw-container input { flex: 1 1 45%; padding: 0.8em; margin: 5px 0; box-sizing: border-box; } .form-inline.password-field { width: 100%; flex-direction: column; gap: 0; } .form-inline.password-field label { margin-bottom: 10px; } .form-inline-2 { text-transform: none; text-align: justify; display: block; vertical-align: top; overflow: hidden; width: 100%; margin: 3px auto; } label, div.label { display: block; text-align: left; margin-bottom: 0; padding-bottom: 0; } input, select, option { font-weight: normal; border: 0; padding: 0.8em; line-height: 20px; resize: none; width: 100%; margin: 5px 0; } input[type=\"submit\"], input[type=\"button\"], button { width: 200px; background-image: linear-gradient(-180deg, #00d775, #00bd68); border-radius: 5px; box-shadow: rgba(0, 0, 0, 0.1) 0 2px 4px; color: #fff; white-space: nowrap; padding: 0.8em; border: 0; cursor: pointer; } input[type=\"submit\"]:hover, input[type=\"button\"]:hover, button:hover { background: #00bd68; } input[type=\"reset\"] { width: 200px; background-image: linear-gradient(-180deg, #fe7b2f, #e73005); border-radius: 5px; box-shadow: rgba(0, 0, 0, 0.1) 0 2px 4px; color: #fff; white-space: nowrap; padding: 0.8em; border: 0; cursor: pointer; } input[type=\"reset\"]:hover { background: #e73005; } input[type=\"checkbox\"], input[type=\"radio\"] { width: 20px; height: 20px; } textarea { border: 0; padding: 0.8em; resize: none; width: 100%; height: 200px; } .form-btn { margin: 0 auto; text-align: center; } .upload-block { margin-bottom: 25px; padding-bottom: 15px; } /* ================================ RESPONSIVE DESIGN (WIP) ================================ */ @media (max-width: 768px) { .form { flex-direction: column; } .form-inline { width: 100%; } } /* ================================ ALERTS ================================ */ .alert .inner { display: block; padding: 6px; margin: 6px; border-radius: 3px; border: 1px solid rgb(180, 180, 180); background-color: rgb(212, 212, 212); text-shadow: none; } .alert.error .inner { border: 1px solid rgb(238, 211, 215); background-color: rgb(242, 222, 222); color: rgb(185, 74, 72); text-shadow: none; } .alert.error .inner b { color: rgb(185, 74, 72); text-shadow: none; } .alert.success .inner { border: 1px solid rgb(214, 233, 198); background-color: rgb(223, 240, 216); color: rgb(70, 136, 71); text-shadow: none; } .alert.success .inner b { color: rgb(70, 136, 71); text-shadow: none; }",
      "tokens": [
        "fonts",
        "import",
        "url",
        "https",
        "fonts",
        "googleapis",
        "com",
        "css2",
        "family",
        "fira",
        "sans",
        "display",
        "swap",
        "globals",
        "div",
        "qtip",
        "background",
        "fefefe",
        "font",
        "normal",
        "8em",
        "fira",
        "sans",
        "sans",
        "serif",
        "line",
        "height",
        "20px",
        "color",
        "444",
        "display",
        "none",
        "padding",
        "10px",
        "index",
        "1000",
        "text",
        "shadow",
        "none",
        "text",
        "align",
        "justify",
        "position",
        "absolute",
        "border",
        "border",
        "radius",
        "5px",
        "max",
        "width",
        "350px",
        "req",
        "color",
        "ff0000",
        "imp",
        "color",
        "ff0000",
        "font",
        "weight",
        "bold",
        "showcredit",
        "form",
        "check",
        "display",
        "none",
        "center",
        "display",
        "flex",
        "justify",
        "content",
        "center",
        "gap",
        "1px",
        "flex",
        "wrap",
        "wrap",
        "align",
        "items",
        "center",
        "stat",
        "width",
        "100",
        "text",
        "align",
        "center",
        "forms",
        "select",
        "optgroup",
        "font",
        "weight",
        "normal",
        "font",
        "style",
        "normal",
        "form",
        "font",
        "size",
        "1rem",
        "margin",
        "auto",
        "width",
        "750px",
        "text",
        "align",
        "center",
        "display",
        "flex",
        "flex",
        "wrap",
        "wrap",
        "gap",
        "20px",
        "justify",
        "content",
        "space",
        "between",
        "form",
        "inline",
        "display",
        "flex",
        "flex",
        "direction",
        "column",
        "gap",
        "0px",
        "box",
        "sizing",
        "border",
        "box",
        "width",
        "48",
        "margin",
        "bottom",
        "10px",
        "margin",
        "top",
        "auto",
        "form",
        "inline",
        "label",
        "form",
        "inline",
        "div",
        "label",
        "display",
        "block",
        "margin",
        "0px",
        "form",
        "inline",
        "input",
        "form",
        "inline",
        "select",
        "width",
        "100",
        "padding",
        "8em",
        "margin",
        "top",
        "5px",
        "margin",
        "bottom",
        "10px",
        "box",
        "sizing",
        "border",
        "box",
        "font",
        "size",
        "1rem",
        "pw",
        "container",
        "display",
        "flex",
        "gap",
        "20px",
        "pw",
        "group",
        "flex",
        "display",
        "flex",
        "flex",
        "direction",
        "column",
        "pw",
        "group",
        "label",
        "margin",
        "bottom",
        "5px",
        "pw",
        "container",
        "input",
        "flex",
        "45",
        "padding",
        "8em",
        "margin",
        "5px",
        "box",
        "sizing",
        "border",
        "box",
        "form",
        "inline",
        "password",
        "field",
        "width",
        "100",
        "flex",
        "direction",
        "column",
        "gap",
        "form",
        "inline",
        "password",
        "field",
        "label",
        "margin",
        "bottom",
        "10px",
        "form",
        "inline",
        "text",
        "transform",
        "none",
        "text",
        "align",
        "justify",
        "display",
        "block",
        "vertical",
        "align",
        "top",
        "overflow",
        "hidden",
        "width",
        "100",
        "margin",
        "3px",
        "auto",
        "label",
        "div",
        "label",
        "display",
        "block",
        "text",
        "align",
        "left",
        "margin",
        "bottom",
        "padding",
        "bottom",
        "input",
        "select",
        "option",
        "font",
        "weight",
        "normal",
        "border",
        "padding",
        "8em",
        "line",
        "height",
        "20px",
        "resize",
        "none",
        "width",
        "100",
        "margin",
        "5px",
        "input",
        "type",
        "submit",
        "input",
        "type",
        "button",
        "button",
        "width",
        "200px",
        "background",
        "image",
        "linear",
        "gradient",
        "180deg",
        "00d775",
        "00bd68",
        "border",
        "radius",
        "5px",
        "box",
        "shadow",
        "rgba",
        "2px",
        "4px",
        "color",
        "fff",
        "white",
        "space",
        "nowrap",
        "padding",
        "8em",
        "border",
        "cursor",
        "pointer",
        "input",
        "type",
        "submit",
        "hover",
        "input",
        "type",
        "button",
        "hover",
        "button",
        "hover",
        "background",
        "00bd68",
        "input",
        "type",
        "reset",
        "width",
        "200px",
        "background",
        "image",
        "linear",
        "gradient",
        "180deg",
        "fe7b2f",
        "e73005",
        "border",
        "radius",
        "5px",
        "box",
        "shadow",
        "rgba",
        "2px",
        "4px",
        "color",
        "fff",
        "white",
        "space",
        "nowrap",
        "padding",
        "8em",
        "border",
        "cursor",
        "pointer",
        "input",
        "type",
        "reset",
        "hover",
        "background",
        "e73005",
        "input",
        "type",
        "checkbox",
        "input",
        "type",
        "radio",
        "width",
        "20px",
        "height",
        "20px",
        "textarea",
        "border",
        "padding",
        "8em",
        "resize",
        "none",
        "width",
        "100",
        "height",
        "200px",
        "form",
        "btn",
        "margin",
        "auto",
        "text",
        "align",
        "center",
        "upload",
        "block",
        "margin",
        "bottom",
        "25px",
        "padding",
        "bottom",
        "15px",
        "responsive",
        "design",
        "wip",
        "media",
        "max",
        "width",
        "768px",
        "form",
        "flex",
        "direction",
        "column",
        "form",
        "inline",
        "width",
        "100",
        "alerts",
        "alert",
        "inner",
        "display",
        "block",
        "padding",
        "6px",
        "margin",
        "6px",
        "border",
        "radius",
        "3px",
        "border",
        "1px",
        "solid",
        "rgb",
        "180",
        "180",
        "180",
        "background",
        "color",
        "rgb",
        "212",
        "212",
        "212",
        "text",
        "shadow",
        "none",
        "alert",
        "error",
        "inner",
        "border",
        "1px",
        "solid",
        "rgb",
        "238",
        "211",
        "215",
        "background",
        "color",
        "rgb",
        "242",
        "222",
        "222",
        "color",
        "rgb",
        "185",
        "74",
        "72",
        "text",
        "shadow",
        "none",
        "alert",
        "error",
        "inner",
        "color",
        "rgb",
        "185",
        "74",
        "72",
        "text",
        "shadow",
        "none",
        "alert",
        "success",
        "inner",
        "border",
        "1px",
        "solid",
        "rgb",
        "214",
        "233",
        "198",
        "background",
        "color",
        "rgb",
        "223",
        "240",
        "216",
        "color",
        "rgb",
        "70",
        "136",
        "71",
        "text",
        "shadow",
        "none",
        "alert",
        "success",
        "inner",
        "color",
        "rgb",
        "70",
        "136",
        "71",
        "text",
        "shadow",
        "none"
      ]
    },
    {
      "charEnd": 4549,
      "charStart": 4541,
      "factId": "hz.web.96403eda21f1efd4.fact.4",
      "kind": "bullet",
      "text": "border",
      "tokens": [
        "border"
      ]
    },
    {
      "charEnd": 4558,
      "charStart": 4550,
      "factId": "hz.web.96403eda21f1efd4.fact.5",
      "kind": "bullet",
      "text": "margin",
      "tokens": [
        "margin"
      ]
    },
    {
      "charEnd": 4565,
      "charStart": 4559,
      "factId": "hz.web.96403eda21f1efd4.fact.6",
      "kind": "bullet",
      "text": "form",
      "tokens": [
        "form"
      ]
    },
    {
      "charEnd": 4573,
      "charStart": 4566,
      "factId": "hz.web.96403eda21f1efd4.fact.7",
      "kind": "bullet",
      "text": "width",
      "tokens": [
        "width"
      ]
    },
    {
      "charEnd": 4580,
      "charStart": 4574,
      "factId": "hz.web.96403eda21f1efd4.fact.8",
      "kind": "bullet",
      "text": "flex",
      "tokens": [
        "flex"
      ]
    },
    {
      "charEnd": 4587,
      "charStart": 4581,
      "factId": "hz.web.96403eda21f1efd4.fact.9",
      "kind": "bullet",
      "text": "text",
      "tokens": [
        "text"
      ]
    },
    {
      "charEnd": 4595,
      "charStart": 4588,
      "factId": "hz.web.96403eda21f1efd4.fact.10",
      "kind": "bullet",
      "text": "color",
      "tokens": [
        "color"
      ]
    },
    {
      "charEnd": 4605,
      "charStart": 4596,
      "factId": "hz.web.96403eda21f1efd4.fact.11",
      "kind": "bullet",
      "text": "display",
      "tokens": [
        "display"
      ]
    }
  ],
  "headings": [
    {
      "charEnd": 13,
      "charStart": 1,
      "headingId": "hz.web.96403eda21f1efd4.heading.1",
      "level": 1,
      "line": 2,
      "text": "aquarel.nu"
    },
    {
      "charEnd": 110,
      "charStart": 100,
      "headingId": "hz.web.96403eda21f1efd4.heading.2",
      "level": 2,
      "line": 8,
      "text": "Summary"
    },
    {
      "charEnd": 4539,
      "charStart": 4528,
      "headingId": "hz.web.96403eda21f1efd4.heading.3",
      "level": 2,
      "line": 14,
      "text": "Keywords"
    },
    {
      "charEnd": 4617,
      "charStart": 4607,
      "headingId": "hz.web.96403eda21f1efd4.heading.4",
      "level": 2,
      "line": 25,
      "text": "Excerpt"
    }
  ],
  "moduleIds": [],
  "path": "runtime/learning/promoted/2026-03-31/96403eda21f1efd4.md",
  "provenance": {
    "charRanges": [
      {
        "end": 7851,
        "start": 0
      }
    ],
    "hash": "e257f903a1ebe800aef87ee03e193bc02833b94b1f54b9173b06811294cd5ac0",
    "sourceType": "web"
  },
  "relations": [],
  "rules": [],
  "scenarios": [],
  "status": "canonical",
  "summary": {
    "bullets": [
      "/* * ================================ * Copyright (c) by Aelyn <https://aelysia.net> and Cerine <https://caelestis.nu> * * This domain exists in a state of continual development, and its governing codes * are subject to ongoing revision.",
      "While critical study and analytical engagement * are permitted, any form of reproduction, appropriation, or misattribution of * this work is strictly prohibited.",
      "* ================================ */ /* ================================ FONTS ================================ */ @import url('https://fonts.googleapis.com/css2?family=Fira+Sans&display=swap'); /* ================================ GLOBALS ================================ */ div#qTip { background: #fefefe; font: normal 0.8em 'Fira Sans', sans-serif; line-height: 20px; color: #444; display: none; padding: 10px; z-index: 1000; text-shadow: none; text-align: justify; position: absolute; border: 0; border-radius: 5px; max-width: 350px; } .req { color: #ff0000; } .imp { color: #ff0000; font-weight: bold; } .showCredit, .form-check { display: none; } .center { display: flex; justify-content: center; gap: 1px; flex-wrap: wrap; align-items: center; } .stat { width: 100%; text-align: center; } /* ================================ FORMS ================================ */ .select optgroup { font-weight: normal; font-style: normal; } .form { font-size: 1rem; margin: 0 auto; width: 750px; text-align: center; display: flex; flex-wrap: wrap; gap: 20px; justify-content: space-between; } .form-inline { display: flex; flex-direction: column; gap: 0px; box-sizing: border-box; width: 48%; margin-bottom: 10px; margin-top: auto; } .form-inline label, .form-inline div.label { display: block; margin: 0px; } .form-inline input, .form-inline select { width: 100%; padding: 0.8em; margin-top: 5px; margin-bottom: 10px; box-sizing: border-box; font-size: 1rem; } .pw-container { display: flex; gap: 20px; } .pw-group { flex: 1; display: flex; flex-direction: column; } .pw-group label { margin-bottom: 5px; } .pw-container input { flex: 1 1 45%; padding: 0.8em; margin: 5px 0; box-sizing: border-box; } .form-inline.password-field { width: 100%; flex-direction: column; gap: 0; } .form-inline.password-field label { margin-bottom: 10px; } .form-inline-2 { text-transform: none; text-align: justify; display: block; vertical-align: top; overflow: hidden; width: 100%; margin: 3px auto; } label, div.label { display: block; text-align: left; margin-bottom: 0; padding-bottom: 0; } input, select, option { font-weight: normal; border: 0; padding: 0.8em; line-height: 20px; resize: none; width: 100%; margin: 5px 0; } input[type=\"submit\"], input[type=\"button\"], button { width: 200px; background-image: linear-gradient(-180deg, #00d775, #00bd68); border-radius: 5px; box-shadow: rgba(0, 0, 0, 0.1) 0 2px 4px; color: #fff; white-space: nowrap; padding: 0.8em; border: 0; cursor: pointer; } input[type=\"submit\"]:hover, input[type=\"button\"]:hover, button:hover { background: #00bd68; } input[type=\"reset\"] { width: 200px; background-image: linear-gradient(-180deg, #fe7b2f, #e73005); border-radius: 5px; box-shadow: rgba(0, 0, 0, 0.1) 0 2px 4px; color: #fff; white-space: nowrap; padding: 0.8em; border: 0; cursor: pointer; } input[type=\"reset\"]:hover { background: #e73005; } input[type=\"checkbox\"], input[type=\"radio\"] { width: 20px; height: 20px; } textarea { border: 0; padding: 0.8em; resize: none; width: 100%; height: 200px; } .form-btn { margin: 0 auto; text-align: center; } .upload-block { margin-bottom: 25px; padding-bottom: 15px; } /* ================================ RESPONSIVE DESIGN (WIP) ================================ */ @media (max-width: 768px) { .form { flex-direction: column; } .form-inline { width: 100%; } } /* ================================ ALERTS ================================ */ .alert .inner { display: block; padding: 6px; margin: 6px; border-radius: 3px; border: 1px solid rgb(180, 180, 180); background-color: rgb(212, 212, 212); text-shadow: none; } .alert.error .inner { border: 1px solid rgb(238, 211, 215); background-color: rgb(242, 222, 222); color: rgb(185, 74, 72); text-shadow: none; } .alert.error .inner b { color: rgb(185, 74, 72); text-shadow: none; } .alert.success .inner { border: 1px solid rgb(214, 233, 198); background-color: rgb(223, 240, 216); color: rgb(70, 136, 71); text-shadow: none; } .alert.success .inner b { color: rgb(70, 136, 71); text-shadow: none; }"
    ],
    "medium": "Source: https://aquarel.nu/assets/css/css.css",
    "short": "Source: https://aquarel.nu/assets/css/css.css",
    "tokens": [
      "aquarel",
      "nu",
      "source",
      "https",
      "aquarel",
      "nu",
      "assets",
      "css",
      "css",
      "css",
      "source",
      "https",
      "aquarel",
      "nu",
      "assets",
      "css",
      "css",
      "css"
    ]
  },
  "title": "aquarel.nu"
}
